<?xml version="1.0" encoding="windows-1251"?>
<string_table>

	<string id="st_wpn_mp9_57">
		<text>Brugger-Thomet MP9-N</text>
	</string>
	<string id="st_wpn_mp9_57_s">
		<text>MP9-N</text>
	</string>
	<string id="st_wpn_mp9_57_descr">
		<text>MP9 - компактный пистолет-пулемет, разработанный и произведенный швейцарской компанией Brugger and Thomet Co. Сам по себе он является дальнейшим развитием проекта Steyr TMP, который был продан компанией Steyr в 2001 году. MP9 обладает высокой скорострельностью - 900 выстрелов в минуту, но при этом относительно прост в управлении и удобен в стрельбе. MP9-N - это более совершенный вариант, стреляющий с увеличенным темпом 1100 выстрелов в минуту. Он эффективен в качестве PDW или для скрытого ношения охранниками и телохранителями. В настоящее время его используют многие полицейские и службы безопасности, в том числе из Франции, Швейцарии и Таиланда. Чтобы усилить его роль в качестве PDW, некоторые техники, обладающие большим мастерством, чем разум, переделали некоторые из этих пистолетов под патрон 5.7x28. В результате получилась удивительно эффективная и недорогая альтернатива P90. \n </text>
	</string>

	<string id="st_mag_mp9_5.7x28">
		<text>Модифицированный магазин 5.7x28 MP9</text>
	</string>
	<string id="st_mag_mp9_5.7x28_descr">
			Модифицированный магазин на 30 патронов, используемый в MP9. Переделан для стрельбы патронами 5,7x28.
	</string>

	<string id="st_mag_mp9_9x19">
		<text>Стандартный магазин 9x19 MP9</text>
	</string>
	<string id="st_mag_mp9_9x19_descr">
			Стандартный магазин 9x19 на 30 патронов, используемый в MP9. Их гораздо интереснее выбрасывать, чем заряжать.
	</string>

</string_table>